<?xml version="1.0" encoding="UTF-8"?>
<database>
    <element audit="true" label="NeedIt" max_length="40" name="x_58872_needit_needit" type="collection">
        <element attributes="edge_encryption_enabled=true" label="Active" max_length="40" name="active" type="string"/>
        <element attributes="edge_encryption_enabled=true" label="Additional Comments" max_length="40" name="additional_comments" type="string"/>
        <element attributes="edge_encryption_enabled=true" label="Created by" max_length="40" name="created_by" type="string"/>
        <element attributes="ignore_filter_on_new=true" default="javascript:global.getNextObjNumberPadded();" label="Number" max_length="40" name="number" type="string"/>
        <element attributes="edge_encryption_enabled=true" label="Open" max_length="40" name="open" type="string"/>
        <element attributes="edge_encryption_enabled=true" label="Opened by" max_length="40" name="opened_by" type="string"/>
        <element attributes="edge_encryption_enabled=true" label="Priority" max_length="40" name="priority" type="string"/>
        <element attributes="edge_encryption_enabled=true" dependent="u_desc" dependent_on_field="u_desc" label="Desc" max_length="100" name="u_desc" type="string" use_dependent_field="true"/>
        <element attributes="edge_encryption_enabled=true" label="Description" max_length="200" name="u_description" type="string"/>
        <element label="Requested for" mandatory="true" max_length="32" name="u_requested_for" reference="sys_user" type="reference"/>
        <element attributes="edge_encryption_enabled=true" choice="1" default="[legal]" label="Request type" mandatory="true" max_length="40" name="u_request_type" type="string">
            <choice>
                <element label="Human Resources" sequence="0" value="[hr]"/>
                <element label="Facilities      [facilities]" sequence="1" value="[facilities]"/>
                <element label="Legal      [legal]" sequence="2" value="[legal]"/>
                <element label="Your Department Choice" sequence="3" value="your choice"/>
            </choice>
        </element>
        <element attributes="edge_encryption_enabled=true" dependent="u_short_description" dependent_on_field="u_short_description" label="Short Description" max_length="50" name="u_short_description" type="string" use_dependent_field="true"/>
        <element attributes="edge_encryption_enabled=true" choice="1" label="State" mandatory="true" max_length="40" name="u_state" type="string">
            <choice>
                <element label="Awaiting Approval" sequence="0" value="14"/>
                <element label="Requested" sequence="1" value="13"/>
                <element label="Approved" sequence="2" value="15"/>
                <element label="Awaiting Feedback" sequence="3" value="16"/>
                <element label="Withdrawn" sequence="4" value="8"/>
            </choice>
        </element>
        <element attributes="edge_encryption_enabled=true" choice="1" default="hr1" label="What needed" mandatory="true" max_length="40" name="u_what_needed" type="string">
            <choice>
                <element label="Human Resources 1" sequence="0" value="hr1"/>
                <element label="Human Resources 2" sequence="1" value="hr2"/>
                <element label="Facilities 1" sequence="2" value="facilities 1"/>
                <element label="Facilities 2" sequence="3" value="facilities 2"/>
                <element label="Legal 1" sequence="4" value="legal 1"/>
                <element label="Legal 2" sequence="5" value="legal 2"/>
                <element label="Your Department Choice 1" sequence="6" value="Your choice 1"/>
                <element label="Your Department Choice 2" sequence="7" value="your choice 2"/>
            </choice>
        </element>
        <element label="When needed" mandatory="true" max_length="40" name="u_when_needed" type="glide_date_time"/>
        <element attributes="edge_encryption_enabled=true" label="Work Notes" max_length="40" name="work_notes" type="string"/>
        <index name="index">
            <element name="u_requested_for"/>
        </index>
    </element>
</database>
